crawles/__init__.py
crawles/_data_save/CsvOpen.py
crawles/_data_save/__init__.py
crawles/_data_save/image_save.py
crawles/_data_save/image_save.pyi
crawles/_speedy/MetaSession.py
crawles/_speedy/MyThread.py
crawles/_speedy/RFPDupeFilter.py
crawles/_speedy/Request.py
crawles/_speedy/Response.py
crawles/_speedy/ThreadPool.py
crawles/_speedy/__init__.py
crawles/_speedy/api.py
crawles/_speedy/api.pyi
crawles/_speedy/curl_analysis.py
crawles/_speedy/curl_analysis.pyi
crawles/_speedy/head_format.py
crawles/_speedy/js_call.py
crawles/_speedy/unicode_conversion.py
crawles/_speedy/user_agent.py
crawles/template/base_crawler.j2
crawles/template/class_crawler.j2
crawles/template/curl_differ.j2
crawles/template/def_crawler.j2
crawles/template/thread_crawler.j2
test/TLS指纹拦截.py
test/__init__.py
test/curl_差异.py
test/demo.py
test/model_unittest.py
test/依次循环获取数据.py
test/北京新发地多线程爬虫.py
test/图片函数获取.py
test/美食杰嵌套获取.py
test/js逆向/__init__.py
test/js逆向/d2.py
test/崔庆才靶场/__init__.py
test/崔庆才靶场/ant09.py
test/崔庆才靶场/demo.py
test/崔庆才靶场/j2.py
test/崔庆才靶场/j3.py
test/崔庆才靶场/j4.py
test/崔庆才靶场/j5.py
test/崔庆才靶场/j6.py
test/崔庆才靶场/js 解密1.py
test/崔庆才靶场/ssr1.py
crawles-0.4.1.dist-info/LICENSE.txt
crawles-0.4.1.dist-info/METADATA
crawles-0.4.1.dist-info/WHEEL
crawles-0.4.1.dist-info/top_level.txt
crawles-0.4.1.dist-info/RECORD
