Metadata-Version: 2.1
Name: crawles
Version: 0.4.1
Summary: 这是一个简单的爬虫封装模块，封装一些请求优化与下载功能
Home-page: https://github.com/kuangjianke/crawles
Author: 苯环
Author-email: 1431705288@qq.com
Classifier: Programming Language :: Python :: 3
Classifier: License :: OSI Approved :: MIT License
Classifier: Operating System :: OS Independent
Requires-Python: >=3.5
License-File: LICENSE.txt
Requires-Dist: aiofiles
Requires-Dist: aiohttp
Requires-Dist: pyexecjs
Requires-Dist: lxml
Requires-Dist: jinja2
Requires-Dist: objprint
Requires-Dist: requests
